{
	"Window": {
		"Toolbar": true,
		"width": 900,
		"height": 470,
		"x": 510,
		"y": 305
	},
	"DownloadColumn": {
		"complete": true,
		"total": true,
		"percent": true,
		"elapsed": true,
		"left": true,
		"speed": true,
		"completed": true,
		"UploadSpeed": true,
		"SortType": 1,
		"Width": {
			"name": 227,
			"complete": 75,
			"total": 70,
			"percent": 217,
			"elapsed": 65,
			"left": 65,
			"speed": 80,
			"UploadSpeed": 81
		}
	},
	"UserInterface": {
		"DeleteConfirmation": true,
		"ShowTrayIcon": true,
		"CloseToTray": true,
		"SoundNotification": true,
		"ApplyRecently": true,
		"ApplyRecent": true
	},
	"PluginOrder": 1,
	"PluginAria2": {
		"launch": true,
		"shutdown": true
	},
	"PluginMedia": {
		"match_mode": 3,
		"quality": 5,
		"type": 1
	},
	"FolderHistory": [
		"\/home\/impsid\/Downloads"
	],
	"AutoSave": 1,
	"AutoSaveInterval": 3
}

